{
  "presets": [
    {
      "id": 3,
      "prefabIndex": 0,
      "position": {
        "X": 431,
        "Y": -117
      }
    },
    {
      "id": 0,
      "prefabIndex": 3,
      "position": {
        "X": 410,
        "Y": 597
      }
    },
    {
      "id": 28,
      "prefabIndex": 1,
      "position": {
        "X": 409,
        "Y": 575
      }
    },
    {
      "id": 29,
      "prefabIndex": 8,
      "position": {
        "X": 276,
        "Y": 350
      }
    },
    {
      "id": 13,
      "prefabIndex": 10,
      "position": {
        "X": 305,
        "Y": 391
      }
    },
    {
      "id": 16,
      "prefabIndex": 10,
      "position": {
        "X": 256,
        "Y": 391
      }
    },
    {
      "id": 21,
      "prefabIndex": 10,
      "position": {
        "X": 302,
        "Y": 647
      }
    },
    {
      "id": 38,
      "prefabIndex": 10,
      "position": {
        "X": 255,
        "Y": 648
      }
    },
    {
      "id": 45,
      "prefabIndex": 10,
      "position": {
        "X": 1088,
        "Y": 632
      }
    },
    {
      "id": 47,
      "prefabIndex": 10,
      "position": {
        "X": 992,
        "Y": 632
      }
    },
    {
      "id": 52,
      "prefabIndex": 10,
      "position": {
        "X": 992,
        "Y": 472
      }
    },
    {
      "id": 53,
      "prefabIndex": 10,
      "position": {
        "X": 1041,
        "Y": 472
      }
    },
    {
      "id": 54,
      "prefabIndex": 10,
      "position": {
        "X": 1088,
        "Y": 472
      }
    },
    {
      "id": 55,
      "prefabIndex": 16,
      "position": {
        "X": 272,
        "Y": 209
      }
    },
    {
      "id": 57,
      "prefabIndex": 17,
      "position": {
        "X": 499,
        "Y": 384
      }
    },
    {
      "id": 58,
      "prefabIndex": 17,
      "position": {
        "X": 617,
        "Y": 608
      }
    },
    {
      "id": 59,
      "prefabIndex": 18,
      "position": {
        "X": 696,
        "Y": 495
      }
    },
    {
      "id": 60,
      "prefabIndex": 18,
      "position": {
        "X": 806,
        "Y": 320
      }
    },
    {
      "id": 63,
      "prefabIndex": 16,
      "position": {
        "X": 464,
        "Y": 497
      }
    },
    {
      "id": 64,
      "prefabIndex": 16,
      "position": {
        "X": 336,
        "Y": 448
      }
    },
    {
      "id": 67,
      "prefabIndex": 15,
      "position": {
        "X": 578,
        "Y": 601
      }
    },
    {
      "id": 68,
      "prefabIndex": 15,
      "position": {
        "X": 569,
        "Y": 490
      }
    },
    {
      "id": 71,
      "prefabIndex": 17,
      "position": {
        "X": 475,
        "Y": 498
      }
    },
    {
      "id": 72,
      "prefabIndex": 18,
      "position": {
        "X": 545,
        "Y": 496
      }
    },
    {
      "id": 73,
      "prefabIndex": 15,
      "position": {
        "X": 497,
        "Y": 488
      }
    },
    {
      "id": 74,
      "prefabIndex": 15,
      "position": {
        "X": 581,
        "Y": 488
      }
    },
    {
      "id": 75,
      "prefabIndex": 15,
      "position": {
        "X": 473,
        "Y": 489
      }
    },
    {
      "id": 76,
      "prefabIndex": 15,
      "position": {
        "X": 557,
        "Y": 489
      }
    },
    {
      "id": 77,
      "prefabIndex": 17,
      "position": {
        "X": 536,
        "Y": 497
      }
    },
    {
      "id": 78,
      "prefabIndex": 16,
      "position": {
        "X": 589,
        "Y": 494
      }
    },
    {
      "id": 79,
      "prefabIndex": 32,
      "position": {
        "X": 475,
        "Y": 504
      }
    },
    {
      "id": 80,
      "prefabIndex": 32,
      "position": {
        "X": 519,
        "Y": 521
      }
    },
    {
      "id": 81,
      "prefabIndex": 32,
      "position": {
        "X": 599,
        "Y": 535
      }
    },
    {
      "id": 82,
      "prefabIndex": 32,
      "position": {
        "X": 487,
        "Y": 503
      }
    },
    {
      "id": 83,
      "prefabIndex": 32,
      "position": {
        "X": 470,
        "Y": 517
      }
    },
    {
      "id": 84,
      "prefabIndex": 32,
      "position": {
        "X": 500,
        "Y": 505
      }
    },
    {
      "id": 85,
      "prefabIndex": 32,
      "position": {
        "X": 467,
        "Y": 507
      }
    },
    {
      "id": 86,
      "prefabIndex": 32,
      "position": {
        "X": 481,
        "Y": 514
      }
    },
    {
      "id": 87,
      "prefabIndex": 32,
      "position": {
        "X": 529,
        "Y": 505
      }
    },
    {
      "id": 88,
      "prefabIndex": 32,
      "position": {
        "X": 542,
        "Y": 518
      }
    },
    {
      "id": 89,
      "prefabIndex": 32,
      "position": {
        "X": 512,
        "Y": 523
      }
    },
    {
      "id": 90,
      "prefabIndex": 32,
      "position": {
        "X": 484,
        "Y": 523
      }
    },
    {
      "id": 91,
      "prefabIndex": 32,
      "position": {
        "X": 462,
        "Y": 507
      }
    },
    {
      "id": 92,
      "prefabIndex": 32,
      "position": {
        "X": 459,
        "Y": 520
      }
    },
    {
      "id": 93,
      "prefabIndex": 32,
      "position": {
        "X": 467,
        "Y": 517
      }
    },
    {
      "id": 94,
      "prefabIndex": 32,
      "position": {
        "X": 489,
        "Y": 509
      }
    },
    {
      "id": 95,
      "prefabIndex": 32,
      "position": {
        "X": 497,
        "Y": 517
      }
    },
    {
      "id": 96,
      "prefabIndex": 32,
      "position": {
        "X": 503,
        "Y": 521
      }
    },
    {
      "id": 97,
      "prefabIndex": 32,
      "position": {
        "X": 526,
        "Y": 512
      }
    },
    {
      "id": 98,
      "prefabIndex": 32,
      "position": {
        "X": 517,
        "Y": 507
      }
    },
    {
      "id": 99,
      "prefabIndex": 32,
      "position": {
        "X": 534,
        "Y": 513
      }
    },
    {
      "id": 100,
      "prefabIndex": 32,
      "position": {
        "X": 554,
        "Y": 518
      }
    },
    {
      "id": 101,
      "prefabIndex": 32,
      "position": {
        "X": 570,
        "Y": 515
      }
    },
    {
      "id": 102,
      "prefabIndex": 32,
      "position": {
        "X": 560,
        "Y": 509
      }
    },
    {
      "id": 103,
      "prefabIndex": 32,
      "position": {
        "X": 545,
        "Y": 520
      }
    },
    {
      "id": 104,
      "prefabIndex": 32,
      "position": {
        "X": 563,
        "Y": 521
      }
    },
    {
      "id": 105,
      "prefabIndex": 32,
      "position": {
        "X": 580,
        "Y": 517
      }
    },
    {
      "id": 106,
      "prefabIndex": 32,
      "position": {
        "X": 583,
        "Y": 532
      }
    },
    {
      "id": 107,
      "prefabIndex": 32,
      "position": {
        "X": 592,
        "Y": 548
      }
    },
    {
      "id": 108,
      "prefabIndex": 32,
      "position": {
        "X": 585,
        "Y": 540
      }
    },
    {
      "id": 109,
      "prefabIndex": 32,
      "position": {
        "X": 583,
        "Y": 536
      }
    },
    {
      "id": 110,
      "prefabIndex": 32,
      "position": {
        "X": 600,
        "Y": 541
      }
    },
    {
      "id": 111,
      "prefabIndex": 32,
      "position": {
        "X": 614,
        "Y": 548
      }
    },
    {
      "id": 112,
      "prefabIndex": 32,
      "position": {
        "X": 636,
        "Y": 516
      }
    },
    {
      "id": 113,
      "prefabIndex": 32,
      "position": {
        "X": 651,
        "Y": 513
      }
    },
    {
      "id": 114,
      "prefabIndex": 32,
      "position": {
        "X": 514,
        "Y": 513
      }
    },
    {
      "id": 115,
      "prefabIndex": 38,
      "position": {
        "X": 599,
        "Y": 519
      }
    },
    {
      "id": 116,
      "prefabIndex": 38,
      "position": {
        "X": 535,
        "Y": 519
      }
    },
    {
      "id": 117,
      "prefabIndex": 38,
      "position": {
        "X": 471,
        "Y": 519
      }
    },
    {
      "id": 118,
      "prefabIndex": 38,
      "position": {
        "X": 664,
        "Y": 518
      }
    },
    {
      "id": 121,
      "prefabIndex": 37,
      "position": {
        "X": 368,
        "Y": 602
      }
    },
    {
      "id": 122,
      "prefabIndex": 37,
      "position": {
        "X": 368,
        "Y": 537
      }
    },
    {
      "id": 123,
      "prefabIndex": 37,
      "position": {
        "X": 368,
        "Y": 474
      }
    },
    {
      "id": 124,
      "prefabIndex": 37,
      "position": {
        "X": 368,
        "Y": 409
      }
    },
    {
      "id": 125,
      "prefabIndex": 37,
      "position": {
        "X": 368,
        "Y": 345
      }
    },
    {
      "id": 131,
      "prefabIndex": 21,
      "position": {
        "X": 400,
        "Y": 297
      }
    },
    {
      "id": 132,
      "prefabIndex": 21,
      "position": {
        "X": 336,
        "Y": 344
      }
    },
    {
      "id": 133,
      "prefabIndex": 21,
      "position": {
        "X": 400,
        "Y": 392
      }
    },
    {
      "id": 138,
      "prefabIndex": 21,
      "position": {
        "X": 664,
        "Y": 568
      }
    },
    {
      "id": 139,
      "prefabIndex": 22,
      "position": {
        "X": 944,
        "Y": 581
      }
    },
    {
      "id": 141,
      "prefabIndex": 22,
      "position": {
        "X": 992,
        "Y": 580
      }
    },
    {
      "id": 142,
      "prefabIndex": 22,
      "position": {
        "X": 1040,
        "Y": 580
      }
    },
    {
      "id": 143,
      "prefabIndex": 22,
      "position": {
        "X": 1088,
        "Y": 581
      }
    },
    {
      "id": 146,
      "prefabIndex": 22,
      "position": {
        "X": 256,
        "Y": 340
      }
    },
    {
      "id": 147,
      "prefabIndex": 22,
      "position": {
        "X": 304,
        "Y": 340
      }
    },
    {
      "id": 148,
      "prefabIndex": 22,
      "position": {
        "X": 464,
        "Y": 564
      }
    },
    {
      "id": 149,
      "prefabIndex": 22,
      "position": {
        "X": 528,
        "Y": 565
      }
    },
    {
      "id": 150,
      "prefabIndex": 22,
      "position": {
        "X": 576,
        "Y": 597
      }
    },
    {
      "id": 152,
      "prefabIndex": 22,
      "position": {
        "X": 624,
        "Y": 596
      }
    },
    {
      "id": 153,
      "prefabIndex": 22,
      "position": {
        "X": 992,
        "Y": 420
      }
    },
    {
      "id": 154,
      "prefabIndex": 22,
      "position": {
        "X": 1040,
        "Y": 420
      }
    },
    {
      "id": 155,
      "prefabIndex": 22,
      "position": {
        "X": 1088,
        "Y": 420
      }
    },
    {
      "id": 158,
      "prefabIndex": 22,
      "position": {
        "X": 624,
        "Y": 373
      }
    },
    {
      "id": 159,
      "prefabIndex": 22,
      "position": {
        "X": 672,
        "Y": 372
      }
    },
    {
      "id": 160,
      "prefabIndex": 22,
      "position": {
        "X": 464,
        "Y": 372
      }
    },
    {
      "id": 161,
      "prefabIndex": 22,
      "position": {
        "X": 512,
        "Y": 372
      }
    },
    {
      "id": 162,
      "prefabIndex": 22,
      "position": {
        "X": 560,
        "Y": 372
      }
    },
    {
      "id": 24,
      "prefabIndex": 8,
      "position": {
        "X": 589,
        "Y": 613
      }
    },
    {
      "id": 9,
      "prefabIndex": 3,
      "position": {
        "X": 1058,
        "Y": 487
      }
    },
    {
      "id": 10,
      "prefabIndex": 0,
      "position": {
        "X": 242,
        "Y": 656
      }
    },
    {
      "id": 5,
      "prefabIndex": 1,
      "position": {
        "X": 429,
        "Y": 598
      }
    },
    {
      "id": 14,
      "prefabIndex": 1,
      "position": {
        "X": 429,
        "Y": 577
      }
    },
    {
      "id": 15,
      "prefabIndex": 40,
      "position": {
        "X": 863,
        "Y": 654
      }
    },
    {
      "id": 6,
      "prefabIndex": 46,
      "position": {
        "X": 722,
        "Y": 537
      }
    },
    {
      "id": 25,
      "prefabIndex": 40,
      "position": {
        "X": 931,
        "Y": 495
      }
    },
    {
      "id": 4,
      "prefabIndex": 0,
      "position": {
        "X": 733,
        "Y": 432
      }
    },
    {
      "id": 26,
      "prefabIndex": 29,
      "position": {
        "X": 728,
        "Y": 808
      }
    },
    {
      "id": 27,
      "prefabIndex": 30,
      "position": {
        "X": 744,
        "Y": 808
      }
    },
    {
      "id": 30,
      "prefabIndex": 30,
      "position": {
        "X": 760,
        "Y": 808
      }
    },
    {
      "id": 31,
      "prefabIndex": 30,
      "position": {
        "X": 776,
        "Y": 808
      }
    },
    {
      "id": 43,
      "prefabIndex": 30,
      "position": {
        "X": 712,
        "Y": 791
      }
    },
    {
      "id": 56,
      "prefabIndex": 26,
      "position": {
        "X": 728,
        "Y": 792
      }
    },
    {
      "id": 62,
      "prefabIndex": 28,
      "position": {
        "X": 680,
        "Y": 776
      }
    },
    {
      "id": 168,
      "prefabIndex": 35,
      "position": {
        "X": 232,
        "Y": 797
      }
    },
    {
      "id": 169,
      "prefabIndex": 35,
      "position": {
        "X": 232,
        "Y": 787
      }
    },
    {
      "id": 170,
      "prefabIndex": 35,
      "position": {
        "X": 248,
        "Y": 797
      }
    },
    {
      "id": 171,
      "prefabIndex": 35,
      "position": {
        "X": 248,
        "Y": 787
      }
    },
    {
      "id": 172,
      "prefabIndex": 35,
      "position": {
        "X": 264,
        "Y": 797
      }
    },
    {
      "id": 173,
      "prefabIndex": 35,
      "position": {
        "X": 264,
        "Y": 787
      }
    },
    {
      "id": 174,
      "prefabIndex": 35,
      "position": {
        "X": 280,
        "Y": 797
      }
    },
    {
      "id": 175,
      "prefabIndex": 35,
      "position": {
        "X": 280,
        "Y": 787
      }
    },
    {
      "id": 176,
      "prefabIndex": 35,
      "position": {
        "X": 296,
        "Y": 797
      }
    },
    {
      "id": 178,
      "prefabIndex": 35,
      "position": {
        "X": 296,
        "Y": 787
      }
    },
    {
      "id": 179,
      "prefabIndex": 35,
      "position": {
        "X": 312,
        "Y": 787
      }
    },
    {
      "id": 180,
      "prefabIndex": 35,
      "position": {
        "X": 312,
        "Y": 797
      }
    },
    {
      "id": 181,
      "prefabIndex": 35,
      "position": {
        "X": 328,
        "Y": 797
      }
    },
    {
      "id": 182,
      "prefabIndex": 35,
      "position": {
        "X": 328,
        "Y": 787
      }
    },
    {
      "id": 183,
      "prefabIndex": 35,
      "position": {
        "X": 344,
        "Y": 797
      }
    },
    {
      "id": 184,
      "prefabIndex": 35,
      "position": {
        "X": 344,
        "Y": 787
      }
    },
    {
      "id": 185,
      "prefabIndex": 35,
      "position": {
        "X": 360,
        "Y": 787
      }
    },
    {
      "id": 186,
      "prefabIndex": 35,
      "position": {
        "X": 360,
        "Y": 797
      }
    },
    {
      "id": 187,
      "prefabIndex": 35,
      "position": {
        "X": 376,
        "Y": 797
      }
    },
    {
      "id": 189,
      "prefabIndex": 35,
      "position": {
        "X": 376,
        "Y": 787
      }
    },
    {
      "id": 190,
      "prefabIndex": 35,
      "position": {
        "X": 392,
        "Y": 787
      }
    },
    {
      "id": 191,
      "prefabIndex": 35,
      "position": {
        "X": 392,
        "Y": 797
      }
    },
    {
      "id": 192,
      "prefabIndex": 35,
      "position": {
        "X": 408,
        "Y": 787
      }
    },
    {
      "id": 193,
      "prefabIndex": 35,
      "position": {
        "X": 408,
        "Y": 797
      }
    },
    {
      "id": 194,
      "prefabIndex": 35,
      "position": {
        "X": 424,
        "Y": 787
      }
    },
    {
      "id": 195,
      "prefabIndex": 35,
      "position": {
        "X": 423,
        "Y": 797
      }
    },
    {
      "id": 196,
      "prefabIndex": 35,
      "position": {
        "X": 441,
        "Y": 787
      }
    },
    {
      "id": 197,
      "prefabIndex": 35,
      "position": {
        "X": 439,
        "Y": 797
      }
    },
    {
      "id": 198,
      "prefabIndex": 35,
      "position": {
        "X": 455,
        "Y": 797
      }
    },
    {
      "id": 199,
      "prefabIndex": 35,
      "position": {
        "X": 455,
        "Y": 787
      }
    },
    {
      "id": 200,
      "prefabIndex": 35,
      "position": {
        "X": 471,
        "Y": 787
      }
    },
    {
      "id": 201,
      "prefabIndex": 35,
      "position": {
        "X": 472,
        "Y": 797
      }
    },
    {
      "id": 203,
      "prefabIndex": 35,
      "position": {
        "X": 488,
        "Y": 797
      }
    },
    {
      "id": 204,
      "prefabIndex": 35,
      "position": {
        "X": 487,
        "Y": 787
      }
    },
    {
      "id": 205,
      "prefabIndex": 35,
      "position": {
        "X": 503,
        "Y": 787
      }
    },
    {
      "id": 206,
      "prefabIndex": 35,
      "position": {
        "X": 504,
        "Y": 797
      }
    },
    {
      "id": 207,
      "prefabIndex": 35,
      "position": {
        "X": 519,
        "Y": 787
      }
    },
    {
      "id": 208,
      "prefabIndex": 35,
      "position": {
        "X": 520,
        "Y": 797
      }
    },
    {
      "id": 209,
      "prefabIndex": 35,
      "position": {
        "X": 535,
        "Y": 787
      }
    },
    {
      "id": 210,
      "prefabIndex": 35,
      "position": {
        "X": 535,
        "Y": 797
      }
    },
    {
      "id": 211,
      "prefabIndex": 35,
      "position": {
        "X": 551,
        "Y": 787
      }
    },
    {
      "id": 212,
      "prefabIndex": 35,
      "position": {
        "X": 551,
        "Y": 797
      }
    },
    {
      "id": 224,
      "prefabIndex": 36,
      "position": {
        "X": 551,
        "Y": 787
      }
    },
    {
      "id": 225,
      "prefabIndex": 36,
      "position": {
        "X": 552,
        "Y": 797
      }
    },
    {
      "id": 226,
      "prefabIndex": 35,
      "position": {
        "X": 568,
        "Y": 862
      }
    },
    {
      "id": 227,
      "prefabIndex": 35,
      "position": {
        "X": 568,
        "Y": 852
      }
    },
    {
      "id": 228,
      "prefabIndex": 35,
      "position": {
        "X": 584,
        "Y": 862
      }
    },
    {
      "id": 230,
      "prefabIndex": 35,
      "position": {
        "X": 600,
        "Y": 862
      }
    },
    {
      "id": 8,
      "prefabIndex": 35,
      "position": {
        "X": 616,
        "Y": 862
      }
    },
    {
      "id": 32,
      "prefabIndex": 35,
      "position": {
        "X": 584,
        "Y": 852
      }
    },
    {
      "id": 36,
      "prefabIndex": 35,
      "position": {
        "X": 600,
        "Y": 852
      }
    },
    {
      "id": 37,
      "prefabIndex": 35,
      "position": {
        "X": 616,
        "Y": 852
      }
    },
    {
      "id": 40,
      "prefabIndex": 35,
      "position": {
        "X": 632,
        "Y": 862
      }
    },
    {
      "id": 41,
      "prefabIndex": 35,
      "position": {
        "X": 632,
        "Y": 852
      }
    },
    {
      "id": 42,
      "prefabIndex": 35,
      "position": {
        "X": 648,
        "Y": 862
      }
    },
    {
      "id": 48,
      "prefabIndex": 35,
      "position": {
        "X": 648,
        "Y": 852
      }
    },
    {
      "id": 49,
      "prefabIndex": 35,
      "position": {
        "X": 664,
        "Y": 862
      }
    },
    {
      "id": 66,
      "prefabIndex": 35,
      "position": {
        "X": 664,
        "Y": 852
      }
    },
    {
      "id": 119,
      "prefabIndex": 35,
      "position": {
        "X": 680,
        "Y": 852
      }
    },
    {
      "id": 126,
      "prefabIndex": 35,
      "position": {
        "X": 680,
        "Y": 862
      }
    },
    {
      "id": 140,
      "prefabIndex": 35,
      "position": {
        "X": 696,
        "Y": 852
      }
    },
    {
      "id": 164,
      "prefabIndex": 35,
      "position": {
        "X": 696,
        "Y": 862
      }
    },
    {
      "id": 165,
      "prefabIndex": 35,
      "position": {
        "X": 712,
        "Y": 852
      }
    },
    {
      "id": 166,
      "prefabIndex": 35,
      "position": {
        "X": 712,
        "Y": 862
      }
    },
    {
      "id": 167,
      "prefabIndex": 35,
      "position": {
        "X": 728,
        "Y": 852
      }
    },
    {
      "id": 177,
      "prefabIndex": 35,
      "position": {
        "X": 728,
        "Y": 862
      }
    },
    {
      "id": 188,
      "prefabIndex": 35,
      "position": {
        "X": 744,
        "Y": 852
      }
    },
    {
      "id": 202,
      "prefabIndex": 35,
      "position": {
        "X": 744,
        "Y": 862
      }
    },
    {
      "id": 213,
      "prefabIndex": 35,
      "position": {
        "X": 760,
        "Y": 852
      }
    },
    {
      "id": 214,
      "prefabIndex": 35,
      "position": {
        "X": 760,
        "Y": 862
      }
    },
    {
      "id": 215,
      "prefabIndex": 35,
      "position": {
        "X": 776,
        "Y": 852
      }
    },
    {
      "id": 217,
      "prefabIndex": 35,
      "position": {
        "X": 792,
        "Y": 852
      }
    },
    {
      "id": 219,
      "prefabIndex": 35,
      "position": {
        "X": 776,
        "Y": 862
      }
    },
    {
      "id": 220,
      "prefabIndex": 35,
      "position": {
        "X": 792,
        "Y": 862
      }
    },
    {
      "id": 221,
      "prefabIndex": 35,
      "position": {
        "X": 808,
        "Y": 852
      }
    },
    {
      "id": 222,
      "prefabIndex": 35,
      "position": {
        "X": 808,
        "Y": 862
      }
    },
    {
      "id": 231,
      "prefabIndex": 35,
      "position": {
        "X": 824,
        "Y": 862
      }
    },
    {
      "id": 232,
      "prefabIndex": 35,
      "position": {
        "X": 824,
        "Y": 852
      }
    },
    {
      "id": 233,
      "prefabIndex": 35,
      "position": {
        "X": 840,
        "Y": 852
      }
    },
    {
      "id": 234,
      "prefabIndex": 35,
      "position": {
        "X": 840,
        "Y": 862
      }
    },
    {
      "id": 235,
      "prefabIndex": 35,
      "position": {
        "X": 856,
        "Y": 852
      }
    },
    {
      "id": 236,
      "prefabIndex": 35,
      "position": {
        "X": 856,
        "Y": 862
      }
    },
    {
      "id": 237,
      "prefabIndex": 35,
      "position": {
        "X": 872,
        "Y": 852
      }
    },
    {
      "id": 238,
      "prefabIndex": 35,
      "position": {
        "X": 872,
        "Y": 862
      }
    },
    {
      "id": 240,
      "prefabIndex": 35,
      "position": {
        "X": 888,
        "Y": 852
      }
    },
    {
      "id": 241,
      "prefabIndex": 35,
      "position": {
        "X": 888,
        "Y": 862
      }
    },
    {
      "id": 242,
      "prefabIndex": 35,
      "position": {
        "X": 904,
        "Y": 852
      }
    },
    {
      "id": 243,
      "prefabIndex": 35,
      "position": {
        "X": 904,
        "Y": 862
      }
    },
    {
      "id": 244,
      "prefabIndex": 35,
      "position": {
        "X": 920,
        "Y": 852
      }
    },
    {
      "id": 245,
      "prefabIndex": 35,
      "position": {
        "X": 920,
        "Y": 862
      }
    },
    {
      "id": 246,
      "prefabIndex": 35,
      "position": {
        "X": 936,
        "Y": 852
      }
    },
    {
      "id": 247,
      "prefabIndex": 35,
      "position": {
        "X": 936,
        "Y": 862
      }
    },
    {
      "id": 248,
      "prefabIndex": 35,
      "position": {
        "X": 952,
        "Y": 852
      }
    },
    {
      "id": 249,
      "prefabIndex": 35,
      "position": {
        "X": 952,
        "Y": 862
      }
    },
    {
      "id": 250,
      "prefabIndex": 35,
      "position": {
        "X": 968,
        "Y": 852
      }
    },
    {
      "id": 267,
      "prefabIndex": 38,
      "position": {
        "X": 232,
        "Y": 767
      }
    },
    {
      "id": 268,
      "prefabIndex": 38,
      "position": {
        "X": 232,
        "Y": 735
      }
    },
    {
      "id": 269,
      "prefabIndex": 38,
      "position": {
        "X": 232,
        "Y": 703
      }
    },
    {
      "id": 270,
      "prefabIndex": 32,
      "position": {
        "X": 336,
        "Y": 782
      }
    },
    {
      "id": 271,
      "prefabIndex": 32,
      "position": {
        "X": 397,
        "Y": 780
      }
    },
    {
      "id": 272,
      "prefabIndex": 32,
      "position": {
        "X": 239,
        "Y": 790
      }
    },
    {
      "id": 273,
      "prefabIndex": 32,
      "position": {
        "X": 560,
        "Y": 795
      }
    },
    {
      "id": 274,
      "prefabIndex": 32,
      "position": {
        "X": 598,
        "Y": 843
      }
    },
    {
      "id": 275,
      "prefabIndex": 32,
      "position": {
        "X": 649,
        "Y": 785
      }
    },
    {
      "id": 276,
      "prefabIndex": 32,
      "position": {
        "X": 724,
        "Y": 846
      }
    },
    {
      "id": 277,
      "prefabIndex": 32,
      "position": {
        "X": 748,
        "Y": 782
      }
    },
    {
      "id": 278,
      "prefabIndex": 32,
      "position": {
        "X": 586,
        "Y": 843
      }
    },
    {
      "id": 279,
      "prefabIndex": 32,
      "position": {
        "X": 403,
        "Y": 785
      }
    },
    {
      "id": 280,
      "prefabIndex": 4,
      "position": {
        "X": 657,
        "Y": 854
      }
    },
    {
      "id": 281,
      "prefabIndex": 4,
      "position": {
        "X": 697,
        "Y": 852
      }
    },
    {
      "id": 283,
      "prefabIndex": 4,
      "position": {
        "X": 689,
        "Y": 832
      }
    },
    {
      "id": 284,
      "prefabIndex": 3,
      "position": {
        "X": 667,
        "Y": 833
      }
    },
    {
      "id": 285,
      "prefabIndex": 3,
      "position": {
        "X": 677,
        "Y": 854
      }
    },
    {
      "id": 1,
      "prefabIndex": 17,
      "position": {
        "X": 622,
        "Y": 784
      }
    },
    {
      "id": 2,
      "prefabIndex": 18,
      "position": {
        "X": 752,
        "Y": 784
      }
    },
    {
      "id": 18,
      "prefabIndex": 41,
      "position": {
        "X": 392,
        "Y": 344
      }
    },
    {
      "id": 19,
      "prefabIndex": 41,
      "position": {
        "X": 344,
        "Y": 344
      }
    },
    {
      "id": 20,
      "prefabIndex": 41,
      "position": {
        "X": 344,
        "Y": 408
      }
    },
    {
      "id": 22,
      "prefabIndex": 41,
      "position": {
        "X": 392,
        "Y": 408
      }
    },
    {
      "id": 23,
      "prefabIndex": 41,
      "position": {
        "X": 392,
        "Y": 472
      }
    },
    {
      "id": 50,
      "prefabIndex": 41,
      "position": {
        "X": 344,
        "Y": 472
      }
    },
    {
      "id": 70,
      "prefabIndex": 41,
      "position": {
        "X": 344,
        "Y": 536
      }
    },
    {
      "id": 129,
      "prefabIndex": 41,
      "position": {
        "X": 392,
        "Y": 536
      }
    },
    {
      "id": 151,
      "prefabIndex": 41,
      "position": {
        "X": 392,
        "Y": 600
      }
    },
    {
      "id": 156,
      "prefabIndex": 41,
      "position": {
        "X": 344,
        "Y": 600
      }
    },
    {
      "id": 255,
      "prefabIndex": 30,
      "position": {
        "X": 408,
        "Y": 216
      }
    },
    {
      "id": 256,
      "prefabIndex": 30,
      "position": {
        "X": 392,
        "Y": 216
      }
    },
    {
      "id": 257,
      "prefabIndex": 30,
      "position": {
        "X": 376,
        "Y": 216
      }
    },
    {
      "id": 259,
      "prefabIndex": 30,
      "position": {
        "X": 360,
        "Y": 216
      }
    },
    {
      "id": 261,
      "prefabIndex": 29,
      "position": {
        "X": 344,
        "Y": 216
      }
    },
    {
      "id": 263,
      "prefabIndex": 28,
      "position": {
        "X": 344,
        "Y": 200
      }
    },
    {
      "id": 288,
      "prefabIndex": 10,
      "position": {
        "X": 272,
        "Y": 248
      }
    },
    {
      "id": 289,
      "prefabIndex": 9,
      "position": {
        "X": 400,
        "Y": 255
      }
    },
    {
      "id": 291,
      "prefabIndex": 11,
      "position": {
        "X": 313,
        "Y": 232
      }
    },
    {
      "id": 293,
      "prefabIndex": 11,
      "position": {
        "X": 279,
        "Y": 223
      }
    },
    {
      "id": 295,
      "prefabIndex": 11,
      "position": {
        "X": 386,
        "Y": 242
      }
    },
    {
      "id": 296,
      "prefabIndex": 11,
      "position": {
        "X": 409,
        "Y": 230
      }
    },
    {
      "id": 299,
      "prefabIndex": 11,
      "position": {
        "X": 354,
        "Y": 202
      }
    },
    {
      "id": 301,
      "prefabIndex": 12,
      "position": {
        "X": 307,
        "Y": 200
      }
    },
    {
      "id": 302,
      "prefabIndex": 13,
      "position": {
        "X": 264,
        "Y": 201
      }
    },
    {
      "id": 304,
      "prefabIndex": 33,
      "position": {
        "X": 407,
        "Y": 361
      }
    },
    {
      "id": 306,
      "prefabIndex": 33,
      "position": {
        "X": 327,
        "Y": 313
      }
    },
    {
      "id": 307,
      "prefabIndex": 39,
      "position": {
        "X": 385,
        "Y": 655
      }
    },
    {
      "id": 308,
      "prefabIndex": 39,
      "position": {
        "X": 319,
        "Y": 399
      }
    },
    {
      "id": 310,
      "prefabIndex": 32,
      "position": {
        "X": 401,
        "Y": 651
      }
    },
    {
      "id": 311,
      "prefabIndex": 32,
      "position": {
        "X": 351,
        "Y": 662
      }
    },
    {
      "id": 312,
      "prefabIndex": 32,
      "position": {
        "X": 323,
        "Y": 640
      }
    },
    {
      "id": 313,
      "prefabIndex": 32,
      "position": {
        "X": 388,
        "Y": 453
      }
    },
    {
      "id": 314,
      "prefabIndex": 32,
      "position": {
        "X": 345,
        "Y": 357
      }
    },
    {
      "id": 315,
      "prefabIndex": 18,
      "position": {
        "X": 482,
        "Y": 576
      }
    },
    {
      "id": 316,
      "prefabIndex": 18,
      "position": {
        "X": 582,
        "Y": 495
      }
    },
    {
      "id": 317,
      "prefabIndex": 17,
      "position": {
        "X": 616,
        "Y": 496
      }
    },
    {
      "id": 318,
      "prefabIndex": 17,
      "position": {
        "X": 692,
        "Y": 784
      }
    },
    {
      "id": 320,
      "prefabIndex": 14,
      "position": {
        "X": 776,
        "Y": 776
      }
    },
    {
      "id": 321,
      "prefabIndex": 13,
      "position": {
        "X": 456,
        "Y": 489
      }
    },
    {
      "id": 322,
      "prefabIndex": 0,
      "position": {
        "X": 650,
        "Y": 688
      }
    },
    {
      "id": 323,
      "prefabIndex": 11,
      "position": {
        "X": 337,
        "Y": 465
      }
    },
    {
      "id": 324,
      "prefabIndex": 11,
      "position": {
        "X": 350,
        "Y": 615
      }
    },
    {
      "id": 326,
      "prefabIndex": 11,
      "position": {
        "X": 526,
        "Y": 583
      }
    },
    {
      "id": 329,
      "prefabIndex": 22,
      "position": {
        "X": 368,
        "Y": 196
      }
    },
    {
      "id": 330,
      "prefabIndex": 21,
      "position": {
        "X": 336,
        "Y": 440
      }
    },
    {
      "id": 331,
      "prefabIndex": 21,
      "position": {
        "X": 344,
        "Y": 568
      }
    },
    {
      "id": 332,
      "prefabIndex": 21,
      "position": {
        "X": 328,
        "Y": 584
      }
    },
    {
      "id": 333,
      "prefabIndex": 21,
      "position": {
        "X": 408,
        "Y": 568
      }
    },
    {
      "id": 335,
      "prefabIndex": 21,
      "position": {
        "X": 392,
        "Y": 504
      }
    },
    {
      "id": 338,
      "prefabIndex": 22,
      "position": {
        "X": 256,
        "Y": 596
      }
    },
    {
      "id": 339,
      "prefabIndex": 22,
      "position": {
        "X": 304,
        "Y": 596
      }
    },
    {
      "id": 345,
      "prefabIndex": 37,
      "position": {
        "X": 592,
        "Y": 794
      }
    },
    {
      "id": 346,
      "prefabIndex": 37,
      "position": {
        "X": 624,
        "Y": 794
      }
    },
    {
      "id": 347,
      "prefabIndex": 37,
      "position": {
        "X": 656,
        "Y": 794
      }
    },
    {
      "id": 350,
      "prefabIndex": 37,
      "position": {
        "X": 688,
        "Y": 794
      }
    },
    {
      "id": 351,
      "prefabIndex": 37,
      "position": {
        "X": 720,
        "Y": 794
      }
    },
    {
      "id": 352,
      "prefabIndex": 37,
      "position": {
        "X": 752,
        "Y": 794
      }
    },
    {
      "id": 353,
      "prefabIndex": 30,
      "position": {
        "X": 696,
        "Y": 791
      }
    },
    {
      "id": 354,
      "prefabIndex": 29,
      "position": {
        "X": 680,
        "Y": 791
      }
    },
    {
      "id": 355,
      "prefabIndex": 30,
      "position": {
        "X": 712,
        "Y": 791
      }
    },
    {
      "id": 356,
      "prefabIndex": 26,
      "position": {
        "X": 728,
        "Y": 791
      }
    },
    {
      "id": 357,
      "prefabIndex": 38,
      "position": {
        "X": 776,
        "Y": 791
      }
    },
    {
      "id": 361,
      "prefabIndex": 31,
      "position": {
        "X": 232,
        "Y": 616
      }
    },
    {
      "id": 362,
      "prefabIndex": 28,
      "position": {
        "X": 232,
        "Y": 600
      }
    },
    {
      "id": 363,
      "prefabIndex": 13,
      "position": {
        "X": 232,
        "Y": 599
      }
    },
    {
      "id": 364,
      "prefabIndex": 25,
      "position": {
        "X": 696,
        "Y": 360
      }
    },
    {
      "id": 365,
      "prefabIndex": 25,
      "position": {
        "X": 713,
        "Y": 360
      }
    },
    {
      "id": 366,
      "prefabIndex": 25,
      "position": {
        "X": 729,
        "Y": 360
      }
    },
    {
      "id": 367,
      "prefabIndex": 25,
      "position": {
        "X": 744,
        "Y": 360
      }
    },
    {
      "id": 368,
      "prefabIndex": 25,
      "position": {
        "X": 761,
        "Y": 360
      }
    },
    {
      "id": 369,
      "prefabIndex": 25,
      "position": {
        "X": 777,
        "Y": 360
      }
    },
    {
      "id": 370,
      "prefabIndex": 25,
      "position": {
        "X": 792,
        "Y": 360
      }
    },
    {
      "id": 373,
      "prefabIndex": 25,
      "position": {
        "X": 920,
        "Y": 424
      }
    },
    {
      "id": 374,
      "prefabIndex": 25,
      "position": {
        "X": 808,
        "Y": 360
      }
    },
    {
      "id": 375,
      "prefabIndex": 25,
      "position": {
        "X": 825,
        "Y": 360
      }
    },
    {
      "id": 376,
      "prefabIndex": 26,
      "position": {
        "X": 841,
        "Y": 360
      }
    },
    {
      "id": 380,
      "prefabIndex": 25,
      "position": {
        "X": 872,
        "Y": 391
      }
    },
    {
      "id": 381,
      "prefabIndex": 25,
      "position": {
        "X": 856,
        "Y": 391
      }
    },
    {
      "id": 382,
      "prefabIndex": 25,
      "position": {
        "X": 888,
        "Y": 391
      }
    },
    {
      "id": 383,
      "prefabIndex": 25,
      "position": {
        "X": 937,
        "Y": 424
      }
    },
    {
      "id": 384,
      "prefabIndex": 25,
      "position": {
        "X": 953,
        "Y": 424
      }
    },
    {
      "id": 385,
      "prefabIndex": 27,
      "position": {
        "X": 840,
        "Y": 376
      }
    },
    {
      "id": 386,
      "prefabIndex": 27,
      "position": {
        "X": 904,
        "Y": 408
      }
    },
    {
      "id": 387,
      "prefabIndex": 26,
      "position": {
        "X": 904,
        "Y": 392
      }
    },
    {
      "id": 388,
      "prefabIndex": 29,
      "position": {
        "X": 840,
        "Y": 393
      }
    },
    {
      "id": 389,
      "prefabIndex": 29,
      "position": {
        "X": 904,
        "Y": 424
      }
    },
    {
      "id": 390,
      "prefabIndex": 31,
      "position": {
        "X": 969,
        "Y": 424
      }
    },
    {
      "id": 391,
      "prefabIndex": 20,
      "position": {
        "X": 379,
        "Y": 316
      }
    },
    {
      "id": 392,
      "prefabIndex": 20,
      "position": {
        "X": 356,
        "Y": 362
      }
    },
    {
      "id": 393,
      "prefabIndex": 20,
      "position": {
        "X": 281,
        "Y": 395
      }
    },
    {
      "id": 396,
      "prefabIndex": 20,
      "position": {
        "X": 231,
        "Y": 375
      }
    },
    {
      "id": 398,
      "prefabIndex": 20,
      "position": {
        "X": 277,
        "Y": 651
      }
    },
    {
      "id": 399,
      "prefabIndex": 20,
      "position": {
        "X": 360,
        "Y": 662
      }
    },
    {
      "id": 401,
      "prefabIndex": 20,
      "position": {
        "X": 678,
        "Y": 620
      }
    },
    {
      "id": 402,
      "prefabIndex": 20,
      "position": {
        "X": 765,
        "Y": 531
      }
    },
    {
      "id": 404,
      "prefabIndex": 20,
      "position": {
        "X": 756,
        "Y": 618
      }
    },
    {
      "id": 405,
      "prefabIndex": 20,
      "position": {
        "X": 793,
        "Y": 569
      }
    },
    {
      "id": 406,
      "prefabIndex": 20,
      "position": {
        "X": 773,
        "Y": 506
      }
    },
    {
      "id": 408,
      "prefabIndex": 20,
      "position": {
        "X": 844,
        "Y": 644
      }
    },
    {
      "id": 409,
      "prefabIndex": 20,
      "position": {
        "X": 780,
        "Y": 700
      }
    },
    {
      "id": 410,
      "prefabIndex": 20,
      "position": {
        "X": 801,
        "Y": 672
      }
    },
    {
      "id": 411,
      "prefabIndex": 20,
      "position": {
        "X": 622,
        "Y": 675
      }
    },
    {
      "id": 412,
      "prefabIndex": 20,
      "position": {
        "X": 588,
        "Y": 643
      }
    },
    {
      "id": 413,
      "prefabIndex": 20,
      "position": {
        "X": 508,
        "Y": 589
      }
    },
    {
      "id": 414,
      "prefabIndex": 20,
      "position": {
        "X": 618,
        "Y": 533
      }
    },
    {
      "id": 415,
      "prefabIndex": 20,
      "position": {
        "X": 616,
        "Y": 527
      }
    },
    {
      "id": 416,
      "prefabIndex": 20,
      "position": {
        "X": 623,
        "Y": 520
      }
    },
    {
      "id": 417,
      "prefabIndex": 20,
      "position": {
        "X": 628,
        "Y": 519
      }
    },
    {
      "id": 418,
      "prefabIndex": 20,
      "position": {
        "X": 569,
        "Y": 517
      }
    },
    {
      "id": 419,
      "prefabIndex": 20,
      "position": {
        "X": 617,
        "Y": 527
      }
    },
    {
      "id": 420,
      "prefabIndex": 20,
      "position": {
        "X": 609,
        "Y": 540
      }
    },
    {
      "id": 421,
      "prefabIndex": 20,
      "position": {
        "X": 600,
        "Y": 544
      }
    },
    {
      "id": 422,
      "prefabIndex": 20,
      "position": {
        "X": 603,
        "Y": 548
      }
    },
    {
      "id": 424,
      "prefabIndex": 11,
      "position": {
        "X": 706,
        "Y": 431
      }
    },
    {
      "id": 425,
      "prefabIndex": 11,
      "position": {
        "X": 752,
        "Y": 432
      }
    },
    {
      "id": 426,
      "prefabIndex": 11,
      "position": {
        "X": 1017,
        "Y": 480
      }
    },
    {
      "id": 428,
      "prefabIndex": 11,
      "position": {
        "X": 916,
        "Y": 323
      }
    },
    {
      "id": 438,
      "prefabIndex": 41,
      "position": {
        "X": 871,
        "Y": 424
      }
    },
    {
      "id": 439,
      "prefabIndex": 41,
      "position": {
        "X": 888,
        "Y": 424
      }
    },
    {
      "id": 440,
      "prefabIndex": 41,
      "position": {
        "X": 872,
        "Y": 584
      }
    },
    {
      "id": 441,
      "prefabIndex": 41,
      "position": {
        "X": 888,
        "Y": 584
      }
    },
    {
      "id": 442,
      "prefabIndex": 41,
      "position": {
        "X": 872,
        "Y": 504
      }
    },
    {
      "id": 443,
      "prefabIndex": 41,
      "position": {
        "X": 887,
        "Y": 504
      }
    },
    {
      "id": 446,
      "prefabIndex": 41,
      "position": {
        "X": 760,
        "Y": 424
      }
    },
    {
      "id": 448,
      "prefabIndex": 41,
      "position": {
        "X": 776,
        "Y": 424
      }
    },
    {
      "id": 449,
      "prefabIndex": 41,
      "position": {
        "X": 680,
        "Y": 424
      }
    },
    {
      "id": 450,
      "prefabIndex": 41,
      "position": {
        "X": 664,
        "Y": 424
      }
    },
    {
      "id": 455,
      "prefabIndex": 15,
      "position": {
        "X": 1104,
        "Y": 584
      }
    },
    {
      "id": 456,
      "prefabIndex": 16,
      "position": {
        "X": 752,
        "Y": 320
      }
    },
    {
      "id": 457,
      "prefabIndex": 11,
      "position": {
        "X": 632,
        "Y": 824
      }
    },
    {
      "id": 458,
      "prefabIndex": 23,
      "position": {
        "X": 808,
        "Y": 682
      }
    },
    {
      "id": 459,
      "prefabIndex": 23,
      "position": {
        "X": 295,
        "Y": 249
      }
    },
    {
      "id": 460,
      "prefabIndex": 11,
      "position": {
        "X": 297,
        "Y": 263
      }
    },
    {
      "id": 461,
      "prefabIndex": 11,
      "position": {
        "X": 684,
        "Y": 653
      }
    },
    {
      "id": 464,
      "prefabIndex": 11,
      "position": {
        "X": 795,
        "Y": 682
      }
    },
    {
      "id": 465,
      "prefabIndex": 11,
      "position": {
        "X": 784,
        "Y": 686
      }
    },
    {
      "id": 466,
      "prefabIndex": 11,
      "position": {
        "X": 785,
        "Y": 690
      }
    },
    {
      "id": 467,
      "prefabIndex": 11,
      "position": {
        "X": 796,
        "Y": 679
      }
    },
    {
      "id": 468,
      "prefabIndex": 11,
      "position": {
        "X": 789,
        "Y": 675
      }
    },
    {
      "id": 469,
      "prefabIndex": 11,
      "position": {
        "X": 773,
        "Y": 685
      }
    },
    {
      "id": 470,
      "prefabIndex": 11,
      "position": {
        "X": 763,
        "Y": 691
      }
    },
    {
      "id": 472,
      "prefabIndex": 11,
      "position": {
        "X": 807,
        "Y": 665
      }
    },
    {
      "id": 473,
      "prefabIndex": 11,
      "position": {
        "X": 796,
        "Y": 694
      }
    },
    {
      "id": 474,
      "prefabIndex": 11,
      "position": {
        "X": 780,
        "Y": 662
      }
    },
    {
      "id": 475,
      "prefabIndex": 39,
      "position": {
        "X": 797,
        "Y": 688
      }
    },
    {
      "id": 476,
      "prefabIndex": 9,
      "position": {
        "X": 560,
        "Y": 432
      }
    },
    {
      "id": 479,
      "prefabIndex": 9,
      "position": {
        "X": 528,
        "Y": 432
      }
    },
    {
      "id": 480,
      "prefabIndex": 19,
      "position": {
        "X": 542,
        "Y": 404
      }
    },
    {
      "id": 481,
      "prefabIndex": 17,
      "position": {
        "X": 938,
        "Y": 320
      }
    },
    {
      "id": 482,
      "prefabIndex": 15,
      "position": {
        "X": 920,
        "Y": 312
      }
    },
    {
      "id": 483,
      "prefabIndex": 14,
      "position": {
        "X": 1111,
        "Y": 424
      }
    },
    {
      "id": 484,
      "prefabIndex": 0,
      "position": {
        "X": 744,
        "Y": 847
      }
    },
    {
      "id": 485,
      "prefabIndex": 0,
      "position": {
        "X": 744,
        "Y": 847
      }
    },
    {
      "id": 486,
      "prefabIndex": 0,
      "position": {
        "X": 744,
        "Y": 847
      }
    },
    {
      "id": 487,
      "prefabIndex": 21,
      "position": {
        "X": 656,
        "Y": 775
      }
    },
    {
      "id": 488,
      "prefabIndex": 20,
      "position": {
        "X": 585,
        "Y": 437
      }
    },
    {
      "id": 493,
      "prefabIndex": 43,
      "position": {
        "X": 68,
        "Y": 816
      }
    },
    {
      "id": 11,
      "prefabIndex": 43,
      "position": {
        "X": 249,
        "Y": 856
      }
    },
    {
      "id": 17,
      "prefabIndex": 43,
      "position": {
        "X": 407,
        "Y": 883
      }
    },
    {
      "id": 34,
      "prefabIndex": 43,
      "position": {
        "X": 637,
        "Y": 905
      }
    },
    {
      "id": 44,
      "prefabIndex": 43,
      "position": {
        "X": 909,
        "Y": 905
      }
    },
    {
      "id": 61,
      "prefabIndex": 22,
      "position": {
        "X": 272,
        "Y": 197
      }
    },
    {
      "id": 65,
      "prefabIndex": 35,
      "position": {
        "X": 968,
        "Y": 862
      }
    },
    {
      "id": 69,
      "prefabIndex": 40,
      "position": {
        "X": 960,
        "Y": 863
      }
    },
    {
      "id": 127,
      "prefabIndex": 55,
      "position": {
        "X": 282,
        "Y": 658
      }
    },
    {
      "id": 130,
      "prefabIndex": 53,
      "position": {
        "X": 310,
        "Y": 251
      }
    },
    {
      "id": 134,
      "prefabIndex": 6,
      "position": {
        "X": 479,
        "Y": 422
      }
    },
    {
      "id": 135,
      "prefabIndex": 6,
      "position": {
        "X": 629,
        "Y": 426
      }
    },
    {
      "id": 35,
      "prefabIndex": 55,
      "position": {
        "X": 714,
        "Y": 686
      }
    },
    {
      "id": 120,
      "prefabIndex": 6,
      "position": {
        "X": 697,
        "Y": 683
      }
    },
    {
      "id": 128,
      "prefabIndex": 6,
      "position": {
        "X": 460,
        "Y": 585
      }
    },
    {
      "id": 137,
      "prefabIndex": 38,
      "position": {
        "X": 951,
        "Y": 776
      }
    },
    {
      "id": 144,
      "prefabIndex": 38,
      "position": {
        "X": 951,
        "Y": 744
      }
    },
    {
      "id": 145,
      "prefabIndex": 38,
      "position": {
        "X": 951,
        "Y": 712
      }
    },
    {
      "id": 157,
      "prefabIndex": 38,
      "position": {
        "X": 951,
        "Y": 680
      }
    },
    {
      "id": 163,
      "prefabIndex": 38,
      "position": {
        "X": 951,
        "Y": 808
      }
    },
    {
      "id": 216,
      "prefabIndex": 0,
      "position": {
        "X": 1008,
        "Y": 368
      }
    },
    {
      "id": 218,
      "prefabIndex": 10,
      "position": {
        "X": 1040,
        "Y": 632
      }
    },
    {
      "id": 229,
      "prefabIndex": 39,
      "position": {
        "X": 1020,
        "Y": 640
      }
    },
    {
      "id": 7,
      "prefabIndex": 59,
      "position": {
        "X": 284,
        "Y": 249
      }
    }
  ]
}